README.md
setup.cfg
setup.py
EarthScan/__init__.py
EarthScan/earthscan.py
EarthScan.egg-info/PKG-INFO
EarthScan.egg-info/SOURCES.txt
EarthScan.egg-info/dependency_links.txt
EarthScan.egg-info/requires.txt
EarthScan.egg-info/top_level.txt